slack_lists_mcp/__init__.py
slack_lists_mcp/__main__.py
slack_lists_mcp/config.py
slack_lists_mcp/models.py
slack_lists_mcp/server.py
slack_lists_mcp/slack_client.py
slack_lists_mcp-0.1.7.dist-info/WHEEL
slack_lists_mcp-0.1.7.dist-info/entry_points.txt
slack_lists_mcp-0.1.7.dist-info/METADATA
slack_lists_mcp-0.1.7.dist-info/RECORD
