Metadata-Version: 2.3
Name: slack-lists-mcp
Version: 0.1.7
Summary: MCP server to operate Slack Lists
Keywords: mcp,slack,lists,api
Author: papasim824
Author-email: papasim824 <papasim824@gmail.co.jp>
License: MIT
Classifier: Development Status :: 3 - Alpha
Classifier: Programming Language :: Python :: 3
Classifier: Programming Language :: Python :: 3.12
Classifier: Programming Language :: Python :: 3.13
Classifier: License :: OSI Approved :: MIT License
Classifier: Operating System :: OS Independent
Classifier: Topic :: Communications :: Chat
Requires-Dist: fastmcp>=2.12.4
Requires-Dist: slack-sdk>=3.36.0
Requires-Dist: pydantic>=2.11.9
Requires-Dist: pydantic-settings>=2.11.0
Requires-Dist: python-dotenv>=1.0.1
Requires-Python: >=3.12
Project-URL: Homepage, https://github.com/ppspps824/slack-lists-mcp
Project-URL: Issues, https://github.com/ppspps824/slack-lists-mcp/issues
Project-URL: Repository, https://github.com/ppspps824/slack-lists-mcp
